microbot/__init__.py
microbot/admin.py
microbot/apps.py
microbot/caching.py
microbot/signals.py
microbot/tasks.py
microbot/urls_api.py
microbot/urls_processing.py
microbot/validators.py
microbot/migrations/0001_initial.py
microbot/migrations/0002_auto_20160414_1051.py
microbot/migrations/0003_auto_20160420_0401.py
microbot/migrations/0004_auto_20160427_0856.py
microbot/migrations/0005_auto_20160428_0510.py
microbot/migrations/0006_auto_20160505_0352.py
microbot/migrations/__init__.py
microbot/models/__init__.py
microbot/models/base.py
microbot/models/bot.py
microbot/models/environment_vars.py
microbot/models/handler.py
microbot/models/hook.py
microbot/models/kik_api.py
microbot/models/messenger_api.py
microbot/models/response.py
microbot/models/state.py
microbot/models/telegram_api.py
microbot/serializers/__init__.py
microbot/serializers/bot.py
microbot/serializers/environment_vars.py
microbot/serializers/handler.py
microbot/serializers/hook.py
microbot/serializers/kik_api.py
microbot/serializers/response.py
microbot/serializers/state.py
microbot/serializers/telegram_api.py
microbot/test/__init__.py
microbot/test/testcases.py
microbot/test/factories/__init__.py
microbot/test/factories/bot.py
microbot/test/factories/handler.py
microbot/test/factories/hook.py
microbot/test/factories/kik_api.py
microbot/test/factories/kik_lib.py
microbot/test/factories/messenger_api.py
microbot/test/factories/messenger_lib.py
microbot/test/factories/response.py
microbot/test/factories/state.py
microbot/test/factories/telegram_api.py
microbot/test/factories/telegram_lib.py
microbot/test/factories/user.py
microbot/views/__init__.py
microbot/views/api/__init__.py
microbot/views/api/base.py
microbot/views/api/bot.py
microbot/views/api/environment_vars.py
microbot/views/api/handler.py
microbot/views/api/hook.py
microbot/views/api/state.py
microbot/views/hooks/__init__.py
microbot/views/hooks/kik_hook.py
microbot-1.7.3.dist-info/DESCRIPTION.rst
microbot-1.7.3.dist-info/METADATA
microbot-1.7.3.dist-info/RECORD
microbot-1.7.3.dist-info/WHEEL
microbot-1.7.3.dist-info/metadata.json
microbot-1.7.3.dist-info/top_level.txt
